somarevex
