Metadata-Version: 1.1
Name: somarevex
Version: 1.0.4
Summary: Soma dois valores e retorna o resultado
Home-page: UNKNOWN
Author: Tiago Batista
Author-email: tiago1805@gmail.com
License: MIT
Keywords: soma sum calc
Platform: UNKNOWN
Classifier: Development Status :: 5 - Production/Stable
Classifier: Intended Audience :: Developers
Classifier: License :: OSI Approved :: MIT License
Classifier: Natural Language :: Portuguese (Brazilian)
Classifier: Operating System :: OS Independent
Classifier: Topic :: Software Development :: Internationalization
Classifier: Topic :: Scientific/Engineering :: Physics
